Workbook

Sheet ⚙️ INPUTS
A1: ⚙️ PARÁMETROS DE CARTERA — Tabla de Inputs Editables
A2: Modifica los campos en AZUL · Los campos en NEGRO son fórmulas automáticas · Los campos en VERDE enlazan otras pestañas
A4: 📊 PARÁMETROS DE MERCADO | E4: 🗓️ PARÁMETROS TEMPORALES
A5: Tasa libre de riesgo anual | B5: 0.02 | C5: Euribor / Bund 10Y · Fuente: ECB | E5: Fecha cotización | F5: 19/02/2026 | G5: Fecha última actualización
A6: Prima de riesgo de mercado | B6: 0.055 | C6: Histórico largo plazo mercado europeo | E6: Horizonte inversión (años) | F6: 10 | G6: Para cálculo de rentabilidad esperada
A7: Inflación esperada (anual) | B7: 0.028 | C7: Objetivo BCE ≈ 2-3% | E7: Frecuencia rebalanceo | F7: Semestral | G7: Anual / Semestral / Trimestral
A8: Tipo impositivo (ganancias cap.) | B8: 0.19 | C8: IRPF España 2025 (tramo general) | E8: Benchmark RF | F8: iBoxx EUR | G8: Índice de referencia RF
A9: Comisión media fondos RF | B9: 0.005 | C9: Estimación GVC Gaesco RF | E9: Benchmark RV | F9: MSCI World | G9: Índice de referencia RV
A10: Comisión media fondos RV | B10: 0.015 | C10: Estimación GVC Gaesco RV | E10: Benchmark Cripto | F10: BTC | G10: Referencia cripto
A11: Comisión media Cripto (exchange) | B11: 0.001 | C11: Estimación media exchange
A12: Rentabilidad objetivo cartera | B12: 0.08 | C12: Meta anual del inversor
A13: Volatilidad objetivo (máx.) | B13: 0.12 | C13: Tolerancia al riesgo
A14: Ratio Sharpe objetivo | B14: 0.8 | C14: Rentabilidad ajustada por riesgo
A16: ⚖️ PESOS OBJETIVO DE CARTERA (editable) | E16: 📈 RENTABILIDADES ESPERADAS POR TIPO
A17: Tipo de Activo | B17: Peso Objetivo % | C17: Peso Actual % (auto) | D17: Desviación (auto) | E17: Tipo de Activo | F17: Rent. Esperada % (input) | G17: Volatilidad Est. % (input) | H17: Sharpe Est. (auto)
A18: Renta Fija | B18: 0.65 | C18: =SUMIF('📋 ACTIVOS'!$B$4:$B$28,"RF",'📋 ACTIVOS'!$F$4:$F$28)/SUM('📋 ACTIVOS'!$F$4:$F$28) -> 0.76518565 | D18: =C18-B18 -> 0.11518565 | E18: Renta Fija | F18: 0.07 | G18: 0.04 | H18: =(F18-$B$5)/G18 -> 1.25
A19: Renta Variable | B19: 0.33 | C19: =SUMIF('📋 ACTIVOS'!$B$4:$B$28,"RV",'📋 ACTIVOS'!$F$4:$F$28)/SUM('📋 ACTIVOS'!$F$4:$F$28) -> 0.21788011 | D19: =C19-B19 -> -0.11211989 | E19: Renta Variable | F19: 0.11 | G19: 0.15 | H19: =(F19-$B$5)/G19 -> 0.6
A20: Criptomonedas | B20: 0.02 | C20: =SUMIF('📋 ACTIVOS'!$B$4:$B$28,"CR",'📋 ACTIVOS'!$F$4:$F$28)/SUM('📋 ACTIVOS'!$F$4:$F$28) -> 0.016934243 | D20: =C20-B20 -> -0.0030657572 | E20: Criptomonedas | F20: 0.18 | G20: 0.65 | H20: =(F20-$B$5)/G20 -> 0.24615385
A21: TOTAL | B21: =SUM(B18:B20) -> 1 | C21: =SUM(C18:C20) -> 1 | D21: =SUM(D18:D20) -> 5.8980598e-17
A23: 🧮 MÉTRICAS GLOBALES DE CARTERA (calculadas automáticamente)
A24: Métrica | B24: Valor | C24: Fórmula/Concepto | E24: Métrica | F24: Valor | G24: Fórmula/Concepto
A25: Rentabilidad esperada cartera | B25: =B18*F18+B19*F19+B20*F20 -> 0.0854 | C25: Rentabilidad esperada anual ponderada
A26: Volatilidad esperada cartera | B26: =SQRT(B18^2*G18^2+B19^2*G19^2+B20^2*G20^2) -> 0.057404268 | C26: Volatilidad simplificada sin correlaciones
A27: Sharpe Ratio cartera | B27: =(B25-'⚙️ INPUTS'!B5)/B26 -> 1.1392881 | C27: Exceso retorno / volatilidad
A28: Rentabilidad sobre coste | B28: =(SUM('📋 ACTIVOS'!F4:F28)-SUM('📋 ACTIVOS'!E4:E28))/SUM('📋 ACTIVOS'!E4:E28) -> 165.58851 | C28: Total realizado sobre inversión
A29: Capital invertido total | B29: =SUM('📋 ACTIVOS'!E4:E28) -> 883.08 | C29: Coste total de adquisición
A30: Valor actual total | B30: =SUM('📋 ACTIVOS'!F4:F28) -> 147110.98 | C30: Valor de mercado actual
A31: Ganancia / Pérdida total | B31: =B30-B29 -> 146227.9 | C31: Plusvalía no realizada total
A32: Rentabilidad esperada (10Y) | B32: =(1+B25)^'⚙️ INPUTS'!B6-1 -> 0.0045173446 | C32: Efecto compuesto al horizonte de inversión
A35: CÓDIGO DE COLORES: 🔵 Azul = Input editable | ⚫ Negro = Fórmula automática | 🟢 Verde = Enlace entre pestañas | 🟡 Fondo amarillo = Celda que requiere atención

Sheet 📋 ACTIVOS
A1: 📋 CARTERA DE ACTIVOS — Datos editables por activo
A2: Los campos en AZUL son inputs editables. Actualiza Precio Hoy y el resto se recalcula automáticamente.
A4: # | B4: Cat. | C4: Nombre del Activo | D4: Títulos | E4: P. Compra (€) | F4: Invertido (€) | G4: Precio Hoy (€) | H4: Valor Actual (€) | I4: G/P (€) | J4: Rent. Total % | K4: YTD % | L4: MTD % | M4: Rent. 2021 % | N4: Peso %
A5: 1 | B5: RF | C5: GVC RF Horizonte | D5: 399.7 | E5: 100.08 | F5: =D5*E5 -> 40001.976 | G5: 115.233 | H5: =D5*G5 -> 46058.63 | I5: =H5-F5 -> 6056.6541 | J5: =IFERROR((H5-F5)/F5,0) -> 0.15140887 | K5: 0.0039 | L5: 0.0015 | M5: 0.1515 | N5: =IFERROR(H5/SUM($H$5:$H$29),0) -> 0.28631312
A6: 2 | B6: RF | C6: GVC RF Flexible CONJUNTA | D6: 2092.25 | E6: 11.06 | F6: =D6*E6 -> 23140.285 | G6: 11.2946 | H6: =D6*G6 -> 23631.127 | I6: =H6-F6 -> 490.84185 | J6: =IFERROR((H6-F6)/F6,0) -> 0.021211573 | K6: 0.0092 | L6: 0.0033 | M6: 0.0195 | N6: =IFERROR(H6/SUM($H$5:$H$29),0) -> 0.14689759
A7: 3 | B7: RF | C7: GVC RF Flexible | D7: 3360.12 | E7: 10.42 | F7: =D7*E7 -> 35012.45 | G7: 11.2946 | H7: =D7*G7 -> 37951.211 | I7: =H7-F7 -> 2938.761 | J7: =IFERROR((H7-F7)/F7,0) -> 0.083934741 | K7: 0.0092 | L7: 0.0033 | M7: 0.0843 | N7: =IFERROR(H7/SUM($H$5:$H$29),0) -> 0.23591517
A8: 4 | B8: RF | C8: GVC Constantfons FI | D8: 1523.52 | E8: 9.46 | F8: =D8*E8 -> 14412.499 | G8: 9.7557 | H8: =D8*G8 -> 14863.004 | I8: =H8-F8 -> 450.50486 | J8: =IFERROR((H8-F8)/F8,0) -> 0.031257928 | K8: 0.0026 | L8: 0.001 | M8: 0.0308 | N8: =IFERROR(H8/SUM($H$5:$H$29),0) -> 0.092392523
A9: 5 | B9: RV | C9: Pictet China Index | D9: 5.555 | E9: 144.01 | F9: =D9*E9 -> 799.97555 | G9: 143.63 | H9: =D9*G9 -> 797.86465 | I9: =H9-F9 -> -2.1109 | J9: =IFERROR((H9-F9)/F9,0) -> -0.0026387056 | K9: -0.0037 | L9: -0.0271 | M9: -0.0027 | N9: =IFERROR(H9/SUM($H$5:$H$29),0) -> 0.0049597462
A10: 6 | B10: RV | C10: GVC Zebra US Small Caps | D10: 79.785 | E10: 92 | F10: =D10*E10 -> 7340.22 | G10: 100.096 | H10: =D10*G10 -> 7986.1594 | I10: =H10-F10 -> 645.93936 | J10: =IFERROR((H10-F10)/F10,0) -> 0.088 | K10: 0.0405 | L10: 0.027 | M10: 0.088 | N10: =IFERROR(H10/SUM($H$5:$H$29),0) -> 0.049644164
A11: 7 | B11: RV | C11: GVC Value Minu A | D11: 760.433 | E11: 8.09 | F11: =D11*E11 -> 6151.903 | G11: 9.12465 | H11: =D11*G11 -> 6938.685 | I11: =H11-F11 -> 786.782 | J11: =IFERROR((H11-F11)/F11,0) -> 0.12789246 | K11: 0.0806 | L11: 0.0655 | M11: 0.1282 | N11: =IFERROR(H11/SUM($H$5:$H$29),0) -> 0.043132775
A12: 8 | B12: RV | C12: GVC VIF Clase A FI | D12: 173.524 | E12: 8.64 | F12: =D12*E12 -> 1499.2474 | G12: 8.9725 | H12: =D12*G12 -> 1556.9441 | I12: =H12-F12 -> 57.69673 | J12: =IFERROR((H12-F12)/F12,0) -> 0.038483796 | K12: 0.0229 | L12: -0.0244 | M12: 0.038 | N12: =IFERROR(H12/SUM($H$5:$H$29),0) -> 0.0096783929
A13: 9 | B13: RV | C13: GVC Small Caps A FI | D13: 91.886 | E13: 15.67 | F13: =D13*E13 -> 1439.8536 | G13: 16.772 | H13: =D13*G13 -> 1541.112 | I13: =H13-F13 -> 101.25837 | J13: =IFERROR((H13-F13)/F13,0) -> 0.070325463 | K13: 0.0584 | L13: 0.0338 | M13: 0.0702 | N13: =IFERROR(H13/SUM($H$5:$H$29),0) -> 0.0095799762
A14: 10 | B14: RV | C14: GVC Japón CONJUNTA | D14: 83.012 | E14: 13.01 | F14: =D14*E14 -> 1079.9861 | G14: 15.123 | H14: =D14*G14 -> 1255.3905 | I14: =H14-F14 -> 175.40436 | J14: =IFERROR((H14-F14)/F14,0) -> 0.16241353 | K14: 0.1145 | L14: 0.0791 | M14: 0.1624 | N14: =IFERROR(H14/SUM($H$5:$H$29),0) -> 0.0078038526
A15: 11 | B15: RV | C15: GVC Japón A FI | D15: 187.792 | E15: 12.25 | F15: =D15*E15 -> 2300.452 | G15: 15.123 | H15: =D15*G15 -> 2839.9784 | I15: =H15-F15 -> 539.52642 | J15: =IFERROR((H15-F15)/F15,0) -> 0.23453061 | K15: 0.1283 | L15: 0.0841 | M15: 0.2348 | N15: =IFERROR(H15/SUM($H$5:$H$29),0) -> 0.017654087
A16: 12 | B16: RV | C16: GVC Global Equity DS A | D16: 116.746 | E16: 15.42 | F16: =D16*E16 -> 1800.2233 | G16: 17.719 | H16: =D16*G16 -> 2068.6224 | I16: =H16-F16 -> 268.39905 | J16: =IFERROR((H16-F16)/F16,0) -> 0.14909209 | K16: 0.0834 | L16: 0.0412 | M16: 0.1492 | N16: =IFERROR(H16/SUM($H$5:$H$29),0) -> 0.012859126
... A29: 25 | B29: CR | C29: Bitcoin | D29: 0.014 | E29: 92864.95 | F29: =D29*E29 -> 1300.1093 | G29: 57160.49 | H29: =D29*G29 -> 800.24686 | I29: =H29-F29 -> -499.86244 | J29: =IFERROR((H29-F29)/F29,0) -> -0.38447724 | K29: -0.2336 | L29: -0.1382 | M29: -0.3845 | N29: =IFERROR(H29/SUM($H$5:$H$29),0) -> 0.0049745547
A30: TOTAL CARTERA | F30: =SUM(F5:F29) -> 148411.09 | G30: ="" | H30: =SUM(H5:H29) -> 160868.04 | I30: =SUM(I5:I29) -> 12456.951 | J30: =IFERROR((H30-F30)/F30,0) -> 0.083935444 | K30: =SUMPRODUCT(N5:N29,K5:K29) -> 0.014577458 | L30: =SUMPRODUCT(N5:N29,L5:L29) -> 0.0090873314 | N30: =SUM(N5:N29) -> 1

Sheet 📊 DASHBOARD
A1: 📊 CUADRO DE MANDOS — CARTERA DE INVERSIÓN GVC GAESCO
A2: Última actualización: — Fuente: ⚙️ INPUTS + 📋 ACTIVOS | Tasa libre de riesgo: 2,00% | Datos en €
B6: VALOR TOTAL CARTERA | F6: GANANCIA / PÉRDIDA
B7: =SUM('📋 ACTIVOS'!H5:H29) -> 160868.04 | F7: =SUM('📋 ACTIVOS'!I5:I29) -> 12456.951
B8: =SUM('📋 ACTIVOS'!H5:H29)-SUM('📋 ACTIVOS'!F5:F29) -> 12456.951 | F8: =IFERROR(SUM('📋 ACTIVOS'!I5:I29)/SUM('📋 ACTIVOS'!F5:F29),0) -> 0.083935444 | J8: Sobre coste total | N8: =COUNTA('📋 ACTIVOS'!C5:C29)&" posiciones" -> 25 posiciones
B12: RENT. ESPERADA ANUAL | F12: VOLATILIDAD ESPERADA
B13: ='⚙️ INPUTS'!B25 -> 0.0854 | F13: ='⚙️ INPUTS'!B26 -> 0.057404268 | J13: ='⚙️ INPUTS'!B27 -> 1.1392881 | N13: ='⚙️ INPUTS'!B5 -> 0.02
B14: Ponderada por pesos objetivo | F14: Estimación sin correlaciones | J14: 25 posiciones activas | N14: =COUNTA('📋 ACTIVOS'!C5:C29)&" posiciones" -> 25 posiciones
A17: ANÁLISIS POR CATEGORÍA DE ACTIVOS
B18: Categoría | C18: Invertido (€) | D18: Valor Actual (€) | E18: G/P (€) | F18: Rent. Total % | G18: YTD % | H18: MTD % | I18: Peso Cartera % | J18: Rent. Esperada % | K18: Volatilidad Est. % | L18: Sharpe Est.
B19: 🟢 Renta Fija | C19: =SUMIF('📋 ACTIVOS'!$B$5:$B$29,"RF",'📋 ACTIVOS'!$F$5:$F$29) -> 112567.21 | D19: =SUMIF('📋 ACTIVOS'!$B$5:$B$29,"RF",'📋 ACTIVOS'!$H$5:$H$29) -> 122503.97 | E19: =IFERROR(SUMPRODUCT(('📋 ACTIVOS'!$B$5:$B$29="RF")*'📋 ACTIVOS'!$H$5:$H$29*'📋 ACTIVOS'!$K$5:$K$29)/SUMIF('📋 ACTIVOS'!$B$5:$B$29,"RF",'📋 ACTIVOS'!$H$5:$H$29),0) -> 0.0064065676 | F19: =IFERROR((C19-B19)/B19,0) -> 0 | G19: =IFERROR(SUMPRODUCT(('📋 ACTIVOS'!$B$5:$B$29="RF")*'📋 ACTIVOS'!$K$5:$K$29*'📋 ACTIVOS'!$N$5:$N$29)/SUMIF('📋 ACTIVOS'!$B$5:$B$29,"RF",'📋 ACTIVOS'!$N$5:$N$29),0) -> 0.0064065676 | H19: =IFERROR(SUMPRODUCT(('📋 ACTIVOS'!$B$5:$B$29="RF")*'📋 ACTIVOS'!$L$5:$L$29*'📋 ACTIVOS'!$N$5:$N$29)/SUMIF('📋 ACTIVOS'!$B$5:$B$29,"RF",'📋 ACTIVOS'!$N$5:$N$29),0) -> 0.0023441906 | I19: =IFERROR(SUMIF('📋 ACTIVOS'!$B$5:$B$29,"RF",'📋 ACTIVOS'!$H$5:$H$29)/SUM('📋 ACTIVOS'!$H$5:$H$29),0) -> 0.7615184 | J19: =INDEX('⚙️ INPUTS'!$F$18:$F$20,1) -> 0.07 | K19: =INDEX('⚙️ INPUTS'!$G$18:$G$20,1) -> 0.04 | L19: =INDEX('⚙️ INPUTS'!$H$18:$H$20,1) -> 1.25
B20: 🔵 Renta Variable | C20: =SUMIF('📋 ACTIVOS'!$B$5:$B$29,"RV",'📋 ACTIVOS'!$F$5:$F$29) -> 32052.556 | D20: =SUMIF('📋 ACTIVOS'!$B$5:$B$29,"RV",'📋 ACTIVOS'!$H$5:$H$29) -> 36493.328 | E20: =IFERROR(SUMPRODUCT(('📋 ACTIVOS'!$B$5:$B$29="RV")*'📋 ACTIVOS'!$H$5:$H$29*'📋 ACTIVOS'!$K$5:$K$29)/SUMIF('📋 ACTIVOS'!$B$5:$B$29,"RV",'📋 ACTIVOS'!$H$5:$H$29),0) -> 0.057384233 | F20: =IFERROR((C20-B20)/B20,0) -> 0 | G20: =IFERROR(SUMPRODUCT(('📋 ACTIVOS'!$B$5:$B$29="RV")*'📋 ACTIVOS'!$K$5:$K$29*'📋 ACTIVOS'!$N$5:$N$29)/SUMIF('📋 ACTIVOS'!$B$5:$B$29,"RV",'📋 ACTIVOS'!$N$5:$N$29),0) -> 0.057384233 | H20: =IFERROR(SUMPRODUCT(('📋 ACTIVOS'!$B$5:$B$29="RV")*'📋 ACTIVOS'!$L$5:$L$29*'📋 ACTIVOS'!$N$5:$N$29)/SUMIF('📋 ACTIVOS'!$B$5:$B$29,"RV",'📋 ACTIVOS'!$N$5:$N$29),0) -> 0.041084154 | I20: =IFERROR(SUMIF('📋 ACTIVOS'!$B$5:$B$29,"RV",'📋 ACTIVOS'!$H$5:$H$29)/SUM('📋 ACTIVOS'!$H$5:$H$29),0) -> 0.22685257 | J20: =INDEX('⚙️ INPUTS'!$F$18:$F$20,2) -> 0.11 | K20: =INDEX('⚙️ INPUTS'!$G$18:$G$20,2) -> 0.15 | L20: =INDEX('⚙️ INPUTS'!$H$18:$H$20,2) -> 0.6
B21: 🟡 Criptomonedas | C21: =SUMIF('📋 ACTIVOS'!$B$5:$B$29,"CR",'📋 ACTIVOS'!$F$5:$F$29) -> 3791.3223 | D21: =SUMIF('📋 ACTIVOS'!$B$5:$B$29,"CR",'📋 ACTIVOS'!$H$5:$H$29) -> 1870.739 | E21: =IFERROR(SUMPRODUCT(('📋 ACTIVOS'!$B$5:$B$29="CR")*'📋 ACTIVOS'!$H$5:$H$29*'📋 ACTIVOS'!$K$5:$K$29)/SUMIF('📋 ACTIVOS'!$B$5:$B$29,"CR",'📋 ACTIVOS'!$H$5:$H$29),0) -> -0.28540833 | F21: =IFERROR((C21-B21)/B21,0) -> 0 | G21: =IFERROR(SUMPRODUCT(('📋 ACTIVOS'!$B$5:$B$29="CR")*'📋 ACTIVOS'!$K$5:$K$29*'📋 ACTIVOS'!$N$5:$N$29)/SUMIF('📋 ACTIVOS'!$B$5:$B$29,"CR",'📋 ACTIVOS'!$N$5:$N$29),0) -> -0.28540833 | H21: =IFERROR(SUMPRODUCT(('📋 ACTIVOS'!$B$5:$B$29="CR")*'📋 ACTIVOS'!$L$5:$L$29*'📋 ACTIVOS'!$N$5:$N$29)/SUMIF('📋 ACTIVOS'!$B$5:$B$29,"CR",'📋 ACTIVOS'!$N$5:$N$29),0) -> -0.17351912 | I21: =IFERROR(SUMIF('📋 ACTIVOS'!$B$5:$B$29,"CR",'📋 ACTIVOS'!$H$5:$H$29)/SUM('📋 ACTIVOS'!$H$5:$H$29),0) -> 0.011629028 | J21: =INDEX('⚙️ INPUTS'!$F$18:$F$20,3) -> 0.18 | K21: =INDEX('⚙️ INPUTS'!$G$18:$G$20,3) -> 0.65 | L21: =INDEX('⚙️ INPUTS'!$H$18:$H$20,3) -> 0.24615385
B22: TOTAL | C22: =SUM(B19:B21) -> 0 | D22: =SUM(C19:C21) -> 148411.09 | E22: =SUM(D19:D21) -> 160868.04 | F22: =IFERROR(D22/B22,0) -> 0 | G22: =SUMPRODUCT(G19:G21,H19:H21)/SUM(H19:H21) -> -0.39892454 | H22: =SUMPRODUCT(I19:I21,H19:H21)/SUM(H19:H21) -> -0.06985377 | I22: =SUM(H19:H21) -> -0.13009078 | J22: =SUMPRODUCT(J19:J21,H19:H21)/SUM(H19:H21) -> 0.20408896 | K22: =SUMPRODUCT(K19:K21,H19:H21)/SUM(H19:H21) -> 0.8188977 | L22: =IFERROR((J22-'⚙️ INPUTS'!B5)/K22,0) -> 0.22480093
A24: RENTABILIDAD ESPERADA Y RIESGO ASUMIDO
B25: Tipo de Activo | C25: Peso Actual | D25: Rent. Esp. % | E25: Contrib. Rent. | F25: Vol. Est. % | G25: Contrib. Vol. | H25: Sharpe Est. | I25: Max Drawdown Est. | J25: Rent. Real YTD | K25: Diferencial (Esp-Real)
B26: 🟢 Renta Fija | C26: =SUMIF('📋 ACTIVOS'!$B$5:$B$29,"RF",'📋 ACTIVOS'!$H$5:$H$29)/SUM('📋 ACTIVOS'!$H$5:$H$29) -> 0.7615184 | D26: =INDEX('⚙️ INPUTS'!$F$18:$F$20,1) -> 0.07 | E26: =C26*D26 -> 0.053306288 | F26: =INDEX('⚙️ INPUTS'!$G$18:$G$20,1) -> 0.04 | G26: =C26*F26 -> 0.030460736 | H26: =IFERROR((D26-'⚙️ INPUTS'!$B$5)/F26,0) -> 1.25 | I26: -0.08 | J26: =IFERROR(SUMPRODUCT(('📋 ACTIVOS'!$B$5:$B$29="RF")*'📋 ACTIVOS'!$K$5:$K$29*'📋 ACTIVOS'!$N$5:$N$29)/SUMIF('📋 ACTIVOS'!$B$5:$B$29,"RF",'📋 ACTIVOS'!$N$5:$N$29),0) -> 0.0064065676 | K26: =D26-J26 -> 0.063593432
B27: 🔵 Renta Variable | C27: =SUMIF('📋 ACTIVOS'!$B$5:$B$29,"RV",'📋 ACTIVOS'!$H$5:$H$29)/SUM('📋 ACTIVOS'!$H$5:$H$29) -> 0.22685257 | D27: =INDEX('⚙️ INPUTS'!$F$18:$F$20,2) -> 0.11 | E27: =C27*D27 -> 0.024953783 | F27: =INDEX('⚙️ INPUTS'!$G$18:$G$20,2) -> 0.15 | G27: =C27*F27 -> 0.034027886 | H27: =IFERROR((D27-'⚙️ INPUTS'!$B$5)/F27,0) -> 0.6 | I27: -0.3 | J27: =IFERROR(SUMPRODUCT(('📋 ACTIVOS'!$B$5:$B$29="RV")*'📋 ACTIVOS'!$K$5:$K$29*'📋 ACTIVOS'!$N$5:$N$29)/SUMIF('📋 ACTIVOS'!$B$5:$B$29,"RV",'📋 ACTIVOS'!$N$5:$N$29),0) -> 0.057384233 | K27: =D27-J27 -> 0.052615767
B28: 🟡 Criptomonedas | C28: =SUMIF('📋 ACTIVOS'!$B$5:$B$29,"CR",'📋 ACTIVOS'!$H$5:$H$29)/SUM('📋 ACTIVOS'!$H$5:$H$29) -> 0.011629028 | D28: =INDEX('⚙️ INPUTS'!$F$18:$F$20,3) -> 0.18 | E28: =C28*D28 -> 0.0020932251 | F28: =INDEX('⚙️ INPUTS'!$G$18:$G$20,3) -> 0.65 | G28: =C28*F28 -> 0.0075588685 | H28: =IFERROR((D28-'⚙️ INPUTS'!$B$5)/F28,0) -> 0.24615385 | I28: -0.78 | J28: =IFERROR(SUMPRODUCT(('📋 ACTIVOS'!$B$5:$B$29="CR")*'📋 ACTIVOS'!$K$5:$K$29*'📋 ACTIVOS'!$N$5:$N$29)/SUMIF('📋 ACTIVOS'!$B$5:$B$29,"CR",'📋 ACTIVOS'!$N$5:$N$29),0) -> -0.28540833 | K28: =D28-J28 -> 0.46540833
B29: CARTERA TOTAL | C29: =SUM(C26:C28) -> 1 | D29: ='⚙️ INPUTS'!B25 -> 0.0854 | E29: =SUM(E26:E28) -> 0.080353296 | F29: ='⚙️ INPUTS'!B26 -> 0.057404268 | G29: =SUM(G26:G28) -> 0.07204749 | H29: ='⚙️ INPUTS'!B27 -> 1.1392881 | I29: =MIN(I26:I28) -> -0.78 | J29: =IFERROR(SUMPRODUCT('📋 ACTIVOS'!$H$5:$H$29*'📋 ACTIVOS'!$K$5:$K$29)/SUM('📋 ACTIVOS'!$H$5:$H$29),0) -> 0.014577458 | K29: =D29-J29 -> 0.070822542
A31: ⚠️ NOTA: Las rentabilidades esperadas y volatilidades son estimaciones. Los datos en azul son editables en ⚙️ INPUTS. Actualiza la columna G (Precio Hoy) en 📋 ACTIVOS para refrescar el cuadro.

Sheet 📉 RIESGO
A1: 📉 ANÁLISIS DE RIESGO — Métricas de riesgo por activo y cartera
A2: Rentabilidad esperada = Rf + β × (Rm - Rf) | Rf = tasa libre de riesgo (editable en ⚙️ INPUTS) | Sharpe = (R - Rf) / σ
A4: Activo | B4: Categoría | C4: Rent. Total | D4: YTD | E4: MTD | F4: Rent. Esp. Cat. | G4: Vol. Est. Cat. | H4: Sharpe Est. | I4: Máx. Drawdown Est.
A5: GVC RF Horizonte | B5: RF | C5: ='📋 ACTIVOS'!J5 -> 0.15140887 | D5: ='📋 ACTIVOS'!K5 -> 0.0039 | E5: ='📋 ACTIVOS'!L5 -> 0.0015 | F5: =INDEX('⚙️ INPUTS'!$F$18:$F$20,1) -> 0.07 | G5: =INDEX('⚙️ INPUTS'!$G$18:$G$20,1) -> 0.04 | H5: =IFERROR((INDEX('⚙️ INPUTS'!$F$18:$F$20,1)-'⚙️ INPUTS'!$B$5)/(INDEX('⚙️ INPUTS'!$G$18:$G$20,1)),0) -> 1.25 | I5: -0.08
A6: GVC RF Flexible CONJUNTA | B6: RF | C6: ='📋 ACTIVOS'!J6 -> 0.021211573 | D6: ='📋 ACTIVOS'!K6 -> 0.0092 | E6: ='📋 ACTIVOS'!L6 -> 0.0033 | F6: =INDEX('⚙️ INPUTS'!$F$18:$F$20,1) -> 0.07 | G6: =INDEX('⚙️ INPUTS'!$G$18:$G$20,1) -> 0.04 | H6: =IFERROR((INDEX('⚙️ INPUTS'!$F$18:$F$20,1)-'⚙️ INPUTS'!$B$5)/(INDEX('⚙️ INPUTS'!$G$18:$G$20,1)),0) -> 1.25 | I6: -0.08
A7: GVC RF Flexible | B7: RF | C7: ='📋 ACTIVOS'!J7 -> 0.083934741 | D7: ='📋 ACTIVOS'!K7 -> 0.0092 | E7: ='📋 ACTIVOS'!L7 -> 0.0033 | F7: =INDEX('⚙️ INPUTS'!$F$18:$F$20,1) -> 0.07 | G7: =INDEX('⚙️ INPUTS'!$G$18:$G$20,1) -> 0.04 | H7: =IFERROR((INDEX('⚙️ INPUTS'!$F$18:$F$20,1)-'⚙️ INPUTS'!$B$5)/(INDEX('⚙️ INPUTS'!$G$18:$G$20,1)),0) -> 1.25 | I7: -0.08
A8: GVC Constantfons FI | B8: RF | C8: ='📋 ACTIVOS'!J8 -> 0.031257928 | D8: ='📋 ACTIVOS'!K8 -> 0.0026 | E8: ='📋 ACTIVOS'!L8 -> 0.001 | F8: =INDEX('⚙️ INPUTS'!$F$18:$F$20,1) -> 0.07 | G8: =INDEX('⚙️ INPUTS'!$G$18:$G$20,1) -> 0.04 | H8: =IFERROR((INDEX('⚙️ INPUTS'!$F$18:$F$20,1)-'⚙️ INPUTS'!$B$5)/(INDEX('⚙️ INPUTS'!$G$18:$G$20,1)),0) -> 1.25 | I8: -0.08
A9: Pictet China Index | B9: RV | C9: ='📋 ACTIVOS'!J9 -> -0.0026387056 | D9: ='📋 ACTIVOS'!K9 -> -0.0037 | E9: ='📋 ACTIVOS'!L9 -> -0.0271 | F9: =INDEX('⚙️ INPUTS'!$F$18:$F$20,2) -> 0.11 | G9: =INDEX('⚙️ INPUTS'!$G$18:$G$20,2) -> 0.15 | H9: =IFERROR((INDEX('⚙️ INPUTS'!$F$18:$F$20,2)-'⚙️ INPUTS'!$B$5)/(INDEX('⚙️ INPUTS'!$G$18:$G$20,2)),0) -> 0.6 | I9: -0.3
A10: GVC Zebra US Small Caps | B10: RV | C10: ='📋 ACTIVOS'!J10 -> 0.088 | D10: ='📋 ACTIVOS'!K10 -> 0.0405 | E10: ='📋 ACTIVOS'!L10 -> 0.027 | F10: =INDEX('⚙️ INPUTS'!$F$18:$F$20,2) -> 0.11 | G10: =INDEX('⚙️ INPUTS'!$G$18:$G$20,2) -> 0.15 | H10: =IFERROR((INDEX('⚙️ INPUTS'!$F$18:$F$20,2)-'⚙️ INPUTS'!$B$5)/(INDEX('⚙️ INPUTS'!$G$18:$G$20,2)),0) -> 0.6 | I10: -0.3
A11: GVC Value Minu A | B11: RV | C11: ='📋 ACTIVOS'!J11 -> 0.12789246 | D11: ='📋 ACTIVOS'!K11 -> 0.0806 | E11: ='📋 ACTIVOS'!L11 -> 0.0655 | F11: =INDEX('⚙️ INPUTS'!$F$18:$F$20,2) -> 0.11 | G11: =INDEX('⚙️ INPUTS'!$G$18:$G$20,2) -> 0.15 | H11: =IFERROR((INDEX('⚙️ INPUTS'!$F$18:$F$20,2)-'⚙️ INPUTS'!$B$5)/(INDEX('⚙️ INPUTS'!$G$18:$G$20,2)),0) -> 0.6 | I11: -0.3
A12: GVC VIF Clase A FI | B12: RV | C12: ='📋 ACTIVOS'!J12 -> 0.038483796 | D12: ='📋 ACTIVOS'!K12 -> 0.0229 | E12: ='📋 ACTIVOS'!L12 -> -0.0244 | F12: =INDEX('⚙️ INPUTS'!$F$18:$F$20,2) -> 0.11 | G12: =INDEX('⚙️ INPUTS'!$G$18:$G$20,2) -> 0.15 | H12: =IFERROR((INDEX('⚙️ INPUTS'!$F$18:$F$20,2)-'⚙️ INPUTS'!$B$5)/(INDEX('⚙️ INPUTS'!$G$18:$G$20,2)),0) -> 0.6 | I12: -0.3
A13: GVC Small Caps A FI | B13: RV | C13: ='📋 ACTIVOS'!J13 -> 0.070325463 | D13: ='📋 ACTIVOS'!K13 -> 0.0584 | E13: ='📋 ACTIVOS'!L13 -> 0.0338 | F13: =INDEX('⚙️ INPUTS'!$F$18:$F$20,2) -> 0.11 | G13: =INDEX('⚙️ INPUTS'!$G$18:$G$20,2) -> 0.15 | H13: =IFERROR((INDEX('⚙️ INPUTS'!$F$18:$F$20,2)-'⚙️ INPUTS'!$B$5)/(INDEX('⚙️ INPUTS'!$G$18:$G$20,2)),0) -> 0.6 | I13: -0.3
A14: GVC Japón CONJUNTA | B14: RV | C14: ='📋 ACTIVOS'!J14 -> 0.16241353 | D14: ='📋 ACTIVOS'!K14 -> 0.1145 | E14: ='📋 ACTIVOS'!L14 -> 0.0791 | F14: =INDEX('⚙️ INPUTS'!$F$18:$F$20,2) -> 0.11 | G14: =INDEX('⚙️ INPUTS'!$G$18:$G$20,2) -> 0.15 | H14: =IFERROR((INDEX('⚙️ INPUTS'!$F$18:$F$20,2)-'⚙️ INPUTS'!$B$5)/(INDEX('⚙️ INPUTS'!$G$18:$G$20,2)),0) -> 0.6 | I14: -0.3
A15: GVC Japón A FI | B15: RV | C15: ='📋 ACTIVOS'!J15 -> 0.23453061 | D15: ='📋 ACTIVOS'!K15 -> 0.1283 | E15: ='📋 ACTIVOS'!L15 -> 0.0841 | F15: =INDEX('⚙️ INPUTS'!$F$18:$F$20,2) -> 0.11 | G15: =INDEX('⚙️ INPUTS'!$G$18:$G$20,2) -> 0.15 | H15: =IFERROR((INDEX('⚙️ INPUTS'!$F$18:$F$20,2)-'⚙️ INPUTS'!$B$5)/(INDEX('⚙️ INPUTS'!$G$18:$G$20,2)),0) -> 0.6 | I15: -0.3
A16: GVC Global Equity DS A | B16: RV | C16: ='📋 ACTIVOS'!J16 -> 0.14909209 | D16: ='📋 ACTIVOS'!K16 -> 0.0834 | E16: ='📋 ACTIVOS'!L16 -> 0.0412 | F16: =INDEX('⚙️ INPUTS'!$F$18:$F$20,2) -> 0.11 | G16: =INDEX('⚙️ INPUTS'!$G$18:$G$20,2) -> 0.15 | H16: =IFERROR((INDEX('⚙️ INPUTS'!$F$18:$F$20,2)-'⚙️ INPUTS'!$B$5)/(INDEX('⚙️ INPUTS'!$G$18:$G$20,2)),0) -> 0.6 | I16: -0.3
A17: GVC Emergentfond FI | B17: RV | C17: ='📋 ACTIVOS'!J17 -> 0.11722236 | D17: ='📋 ACTIVOS'!K17 -> 0.0754 | E17: ='📋 ACTIVOS'!L17 -> 0.021 | F17: =INDEX('⚙️ INPUTS'!$F$18:$F$20,2) -> 0.11 | G17: =INDEX('⚙️ INPUTS'!$G$18:$G$20,2) -> 0.15 | H17: =IFERROR((INDEX('⚙️ INPUTS'!$F$18:$F$20,2)-'⚙️ INPUTS'!$B$5)/(INDEX('⚙️ INPUTS'!$G$18:$G$20,2)),0) -> 0.6 | I17: -0.3
A18: GVC 300 Places CONJUNTA | B18: RV | C18: ='📋 ACTIVOS'!J18 -> 0.091523688 | D18: ='📋 ACTIVOS'!K18 -> 0.035 | E18: ='📋 ACTIVOS'!L18 -> 0.0449 | F18: =INDEX('⚙️ INPUTS'!$F$18:$F$20,2) -> 0.11 | G18: =INDEX('⚙️ INPUTS'!$G$18:$G$20,2) -> 0.15 | H18: =IFERROR((INDEX('⚙️ INPUTS'!$F$18:$F$20,2)-'⚙️ INPUTS'!$B$5)/(INDEX('⚙️ INPUTS'!$G$18:$G$20,2)),0) -> 0.6 | I18: -0.3
A19: GVC 300 Places Worldwide | B19: RV | C19: ='📋 ACTIVOS'!J19 -> 0.28579186 | D19: ='📋 ACTIVOS'!K19 -> 0.0375 | E19: ='📋 ACTIVOS'!L19 -> 0.0481 | F19: =INDEX('⚙️ INPUTS'!$F$18:$F$20,2) -> 0.11 | G19: =INDEX('⚙️ INPUTS'!$G$18:$G$20,2) -> 0.15 | H19: =IFERROR((INDEX('⚙️ INPUTS'!$F$18:$F$20,2)-'⚙️ INPUTS'!$B$5)/(INDEX('⚙️ INPUTS'!$G$18:$G$20,2)),0) -> 0.6 | I19: -0.3
A20: Fidelity S&P 500 Index | B20: RV | C20: ='📋 ACTIVOS'!J20 -> 0.063548148 | D20: ='📋 ACTIVOS'!K20 -> -0.0038 | E20: ='📋 ACTIVOS'!L20 -> 0.0007 | F20: =INDEX('⚙️ INPUTS'!$F$18:$F$20,2) -> 0.11 | G20: =INDEX('⚙️ INPUTS'!$G$18:$G$20,2) -> 0.15 | H20: =IFERROR((INDEX('⚙️ INPUTS'!$F$18:$F$20,2)-'⚙️ INPUTS'!$B$5)/(INDEX('⚙️ INPUTS'!$G$18:$G$20,2)),0) -> 0.6 | I20: -0.3
A21: Fidelity MSCI World | B21: RV | C21: ='📋 ACTIVOS'!J21 -> 0.085158526 | D21: ='📋 ACTIVOS'!K21 -> 0.0161 | E21: ='📋 ACTIVOS'!L21 -> 0.0122 | F21: =INDEX('⚙️ INPUTS'!$F$18:$F$20,2) -> 0.11 | G21: =INDEX('⚙️ INPUTS'!$G$18:$G$20,2) -> 0.15 | H21: =IFERROR((INDEX('⚙️ INPUTS'!$F$18:$F$20,2)-'⚙️ INPUTS'!$B$5)/(INDEX('⚙️ INPUTS'!$G$18:$G$20,2)),0) -> 0.6 | I21: -0.3
A22: XRP | B22: CR | C22: ='📋 ACTIVOS'!J22 -> -0.34590094 | D22: ='📋 ACTIVOS'!K22 -> -0.2473 | E22: ='📋 ACTIVOS'!L22 -> -0.1455 | F22: =INDEX('⚙️ INPUTS'!$F$18:$F$20,3) -> 0.18 | G22: =INDEX('⚙️ INPUTS'!$G$18:$G$20,3) -> 0.65 | H22: =IFERROR((INDEX('⚙️ INPUTS'!$F$18:$F$20,3)-'⚙️ INPUTS'!$B$5)/(INDEX('⚙️ INPUTS'!$G$18:$G$20,3)),0) -> 0.24615385 | I22: -0.78
A23: Sui | B23: CR | C23: ='📋 ACTIVOS'!J23 -> -0.65310189 | D23: ='📋 ACTIVOS'!K23 -> -0.3455 | E23: ='📋 ACTIVOS'!L23 -> -0.19 | F23: =INDEX('⚙️ INPUTS'!$F$18:$F$20,3) -> 0.18 | G23: =INDEX('⚙️ INPUTS'!$G$18:$G$20,3) -> 0.65 | H23: =IFERROR((INDEX('⚙️ INPUTS'!$F$18:$F$20,3)-'⚙️ INPUTS'!$B$5)/(INDEX('⚙️ INPUTS'!$G$18:$G$20,3)),0) -> 0.24615385 | I23: -0.78
A24: Solana | B24: CR | C24: ='📋 ACTIVOS'!J24 -> -0.5119389 | D24: ='📋 ACTIVOS'!K24 -> -0.3344 | E24: ='📋 ACTIVOS'!L24 -> -0.2061 | F24: =INDEX('⚙️ INPUTS'!$F$18:$F$20,3) -> 0.18 | G24: =INDEX('⚙️ INPUTS'!$G$18:$G$20,3) -> 0.65 | H24: =IFERROR((INDEX('⚙️ INPUTS'!$F$18:$F$20,3)-'⚙️ INPUTS'!$B$5)/(INDEX('⚙️ INPUTS'!$G$18:$G$20,3)),0) -> 0.24615385 | I24: -0.78
A25: Pump.fun | B25: CR | C25: ='📋 ACTIVOS'!J25 -> -0.799 | D25: ='📋 ACTIVOS'!K25 -> 0.0485 | E25: ='📋 ACTIVOS'!L25 -> -0.2445 | F25: =INDEX('⚙️ INPUTS'!$F$18:$F$20,3) -> 0.18 | G25: =INDEX('⚙️ INPUTS'!$G$18:$G$20,3) -> 0.65 | H25: =IFERROR((INDEX('⚙️ INPUTS'!$F$18:$F$20,3)-'⚙️ INPUTS'!$B$5)/(INDEX('⚙️ INPUTS'!$G$18:$G$20,3)),0) -> 0.24615385 | I25: -0.78
A26: Pudgy Penguins | B26: CR | C26: ='📋 ACTIVOS'!J26 -> -0.78233333 | D26: ='📋 ACTIVOS'!K26 -> -0.2472 | E26: ='📋 ACTIVOS'!L26 -> -0.1511 | F26: =INDEX('⚙️ INPUTS'!$F$18:$F$20,3) -> 0.18 | G26: =INDEX('⚙️ INPUTS'!$G$18:$G$20,3) -> 0.65 | H26: =IFERROR((INDEX('⚙️ INPUTS'!$F$18:$F$20,3)-'⚙️ INPUTS'!$B$5)/(INDEX('⚙️ INPUTS'!$G$18:$G$20,3)),0) -> 0.24615385 | I26: -0.78
A27: Linea | B27: CR | C27: ='📋 ACTIVOS'!J27 -> -0.661 | D27: ='📋 ACTIVOS'!K27 -> -0.4656 | E27: ='📋 ACTIVOS'!L27 -> -0.2585 | F27: =INDEX('⚙️ INPUTS'!$F$18:$F$20,3) -> 0.18 | G27: =INDEX('⚙️ INPUTS'!$G$18:$G$20,3) -> 0.65 | H27: =IFERROR((INDEX('⚙️ INPUTS'!$F$18:$F$20,3)-'⚙️ INPUTS'!$B$5)/(INDEX('⚙️ INPUTS'!$G$18:$G$20,3)),0) -> 0.24615385 | I27: -0.78
A28: Kaspa | B28: CR | C28: ='📋 ACTIVOS'!J28 -> -0.56885714 | D28: ='📋 ACTIVOS'!K28 -> -0.2977 | E28: ='📋 ACTIVOS'!L28 -> -0.076 | F28: =INDEX('⚙️ INPUTS'!$F$18:$F$20,3) -> 0.18 | G28: =INDEX('⚙️ INPUTS'!$G$18:$G$20,3) -> 0.65 | H28: =IFERROR((INDEX('⚙️ INPUTS'!$F$18:$F$20,3)-'⚙️ INPUTS'!$B$5)/(INDEX('⚙️ INPUTS'!$G$18:$G$20,3)),0) -> 0.24615385 | I28: -0.78
A29: Bitcoin | B29: CR | C29: ='📋 ACTIVOS'!J29 -> -0.38447724 | D29: ='📋 ACTIVOS'!K29 -> -0.2336 | E29: ='📋 ACTIVOS'!L29 -> -0.1382 | F29: =INDEX('⚙️ INPUTS'!$F$18:$F$20,3) -> 0.18 | G29: =INDEX('⚙️ INPUTS'!$G$18:$G$20,3) -> 0.65 | H29: =IFERROR((INDEX('⚙️ INPUTS'!$F$18:$F$20,3)-'⚙️ INPUTS'!$B$5)/(INDEX('⚙️ INPUTS'!$G$18:$G$20,3)),0) -> 0.24615385 | I29: -0.78
A30: CARTERA TOTAL | C30: ='📋 ACTIVOS'!J30 -> 0.083935444 | D30: ='📋 ACTIVOS'!K30 -> 0.014577458 | E30: ='📋 ACTIVOS'!L30 -> 0.0090873314 | F30: ='⚙️ INPUTS'!B25 -> 0.0854 | G30: ='⚙️ INPUTS'!B26 -> 0.057404268 | H30: ='⚙️ INPUTS'!B27 -> 1.1392881 | I30: =MIN(E5:E29) -> -0.2585
A32: 📌 INTERPRETACIÓN DEL RATIO SHARPE: >1.0 = Excelente | 0.5-1.0 = Bueno | 0-0.5 = Aceptable | <0 = La inversión no compensa el riesgo asumido
A33: 📌 MÁXIMO DRAWDOWN: Caída máxima estimada desde máximos en escenario bajista severo. RF: −8% | RV: −30% | Cripto: −78% (valores reales actuales)
A34: 📌 VOLATILIDAD ESPERADA: Estimación anualizada. RF ~4% | RV ~15% | Cripto ~65%. Editable en ⚙️ INPUTS para ajustar según condiciones de mercado

Sheet 🔍 ANÁLISIS
A1: 🔍 ANÁLISIS EN PROFUNDIDAD — Hallazgos, Alertas y Recomendaciones
A3: 📊 SCORECARD DE CARTERA
A4: Dimensión | B4: Score (1-10) | C4: Peso | D4: Score Ponderado | E4: Benchmark | F4: vs Benchmark | G4: Semáforo
A5: Rentabilidad total | B5: 7.5 | C5: 0.25 | D5: =B5*C5 -> 1.875 | E5: =IFERROR((SUM('📋 ACTIVOS'!H5:H29)-SUM('📋 ACTIVOS'!F5:F29))/SUM('📋 ACTIVOS'!F5:F29),0) -> 0.083935444 | F5: =B5/10-E5 -> 0.66606456 | G5: =IF(D5>=E5*25,"🟢","🔴") -> 🔴
A6: Gestión del riesgo | B6: 6 | C6: 0.2 | D6: =B6*C6 -> 1.2 | E6: ='⚙️ INPUTS'!B27 -> 1.1392881 | F6: =B6/10-E6 -> -0.53928811 | G6: =IF(D6>=2,"🟢",IF(D6>=1,"🟡","🔴")) -> 🟡
A7: Diversificación | B7: 5.5 | C7: 0.2 | D7: =B7*C7 -> 1.1 | E7: 8 | F7: =B7-E7 -> -2.5 | G7: =IF(B7>=7,"🟢",IF(B7>=5,"🟡","🔴")) -> 🟡
A8: Calidad de activos | B8: 6.5 | C8: 0.15 | D8: =B8*C8 -> 0.975 | E8: 7 | F8: =B8-E8 -> -0.5 | G8: =IF(B8>=7,"🟢",IF(B8>=5,"🟡","🔴")) -> 🟡
A9: Coste (comisiones) | B9: 7 | C9: 0.1 | D9: =B9*C9 -> 0.7 | E9: 6 | F9: =B9-E9 -> 1 | G9: =IF(B9>=6,"🟢",IF(B9>=4,"🟡","🔴")) -> 🟢
A10: Liquidez | B10: 8 | C10: 0.1 | D10: =B10*C10 -> 0.8 | E10: 8 | F10: =B10-E10 -> 0 | G10: =IF(B10>=7,"🟢",IF(B10>=5,"🟡","🔴")) -> 🟢
A11: SCORE GLOBAL CARTERA | B11: =SUM(D5:D10)/SUM(C5:C10) -> 6.65 | C11: =IF(B11>=8,"Excelente 🌟",IF(B11>=6,"Bueno ✅",IF(B11>=4,"Mejorable ⚠️","Deficiente 🔴"))) -> Bueno ✅
A13: 💡 RECOMENDACIONES ACCIONABLES
A14: Prioridad | B14: Tipo | C14: Activo / Área | D14: Acción Recomendada | E14: Impacto Esperado | F14: Plazo | G14: Estado
A15: 🔴 ALTA | B15: Vender | C15: Cripto menores (4) | D15: Liquidar Pump.fun, Pudgy, Linea, Kaspa (−66% a −78%). Aceptar pérdidas y reinvertir en RV | E15: +Rent., −Riesgo | F15: Inmediato | G15: Pendiente
A16: 🔴 ALTA | B16: Rebalanceo | C16: Peso RV actual 21.8% | D16: Incrementar RV al 30-33% redirigiendo nuevas aportaciones (objetivo 65/33/2) | E16: +Rent. esperada | F16: 6-12 meses | G16: Pendiente
A17: 🟡 MEDIA | B17: Diversif. | C17: GVC Gaesco >72% | D17: Añadir fondos de otras gestoras (Vanguard, iShares, Amundi) para reducir riesgo gestora | E17: −Riesgo conc. | F17: 12 meses | G17: Pendiente
A18: 🟡 MEDIA | B18: Comprar | C18: GVC Japón / 300 Places | D18: En correcciones ≥5%, incrementar estas posiciones (+22-29% acumulado, mejor momentum) | E18: +Rent. esperada | F18: Oportunista | G18: Activo
A19: 🟡 MEDIA | B19: Revisar | C19: Pictet China (−0.27% total) | D19: Evaluar tesis de inversión China. Si macro no mejora en 6 meses, rotar a Emergentes | E19: Neutral/positivo | F19: 6 meses | G19: Pendiente
A20: 🟢 BAJA | B20: Simplif. | C20: Posiciones CONJUNTA+Normal | D20: Consolidar GVC Japón, 300 Places y RF Flexible para simplificar seguimiento | E20: Operativo | F20: 12 meses | G20: Pendiente
A21: 🟢 BAJA | B21: Mantener | C21: Bitcoin + Solana (DCA) | D21: En caídas ≥15%, considerar DCA limitado (máx. €500). Resto de cripto: no promediar | E21: Long-term option | F21: Oportunista | G21: Activo
A24: 📉 ANÁLISIS DE ESCENARIOS — Impacto en la cartera ante distintos shocks de mercado
A25: Escenario | B25: Shock RF | C25: Shock RV | D25: Shock Cripto | E25: Impacto Cartera Est. | F25: Valor Cartera Est. | G25: Pérdida Estimada
A26: 🟢 Escenario favorable | B26: 0.06 | C26: 0.2 | D26: 0.4 | E26: =(SUMIF('📋 ACTIVOS'!$B$5:$B$29,"RF",'📋 ACTIVOS'!$H$5:$H$29)/SUM('📋 ACTIVOS'!$H$5:$H$29))*B26+(SUMIF('📋 ACTIVOS'!$B$5:$B$29,"RV",'📋 ACTIVOS'!$H$5:$H$29)/SUM('📋 ACTIVOS'!$H$5:$H$29))*C26+(SUMIF('📋 ACTIVOS'!$B$5:$B$29,"CR",'📋 ACTIVOS'!$H$5:$H$29)/SUM('📋 ACTIVOS'!$H$5:$H$29))*D26 -> 0.09571323 | F26: =SUM('📋 ACTIVOS'!H5:H29)*(1+E26) -> 176265.24 | G26: =F26-SUM('📋 ACTIVOS'!H5:H29) -> 15397.2
A27: ⚪ Escenario base | B27: 0.04 | C27: 0.1 | D27: 0 | E27: =(SUMIF('📋 ACTIVOS'!$B$5:$B$29,"RF",'📋 ACTIVOS'!$H$5:$H$29)/SUM('📋 ACTIVOS'!$H$5:$H$29))*B27+(SUMIF('📋 ACTIVOS'!$B$5:$B$29,"RV",'📋 ACTIVOS'!$H$5:$H$29)/SUM('📋 ACTIVOS'!$H$5:$H$29))*C27+(SUMIF('📋 ACTIVOS'!$B$5:$B$29,"CR",'📋 ACTIVOS'!$H$5:$H$29)/SUM('📋 ACTIVOS'!$H$5:$H$29))*D27 -> 0.053145993 | F27: =SUM('📋 ACTIVOS'!H5:H29)*(1+E27) -> 169417.53 | G27: =F27-SUM('📋 ACTIVOS'!H5:H29) -> 8549.4917
A28: 🟡 Corrección moderada | B28: -0.04 | C28: -0.15 | D28: -0.3 | E28: =(SUMIF('📋 ACTIVOS'!$B$5:$B$29,"RF",'📋 ACTIVOS'!$H$5:$H$29)/SUM('📋 ACTIVOS'!$H$5:$H$29))*B28+(SUMIF('📋 ACTIVOS'!$B$5:$B$29,"RV",'📋 ACTIVOS'!$H$5:$H$29)/SUM('📋 ACTIVOS'!$H$5:$H$29))*C28+(SUMIF('📋 ACTIVOS'!$B$5:$B$29,"CR",'📋 ACTIVOS'!$H$5:$H$29)/SUM('📋 ACTIVOS'!$H$5:$H$29))*D28 -> -0.06797733 | F28: =SUM('📋 ACTIVOS'!H5:H29)*(1+E28) -> 149932.66 | G28: =F28-SUM('📋 ACTIVOS'!H5:H29) -> -10935.38
A29: 🔴 Mercado bajista | B29: -0.08 | C29: -0.3 | D29: -0.6 | E29: =(SUMIF('📋 ACTIVOS'!$B$5:$B$29,"RF",'📋 ACTIVOS'!$H$5:$H$29)/SUM('📋 ACTIVOS'!$H$5:$H$29))*B29+(SUMIF('📋 ACTIVOS'!$B$5:$B$29,"RV",'📋 ACTIVOS'!$H$5:$H$29)/SUM('📋 ACTIVOS'!$H$5:$H$29))*C29+(SUMIF('📋 ACTIVOS'!$B$5:$B$29,"CR",'📋 ACTIVOS'!$H$5:$H$29)/SUM('📋 ACTIVOS'!$H$5:$H$29))*D29 -> -0.13595466 | F29: =SUM('📋 ACTIVOS'!H5:H29)*(1+E29) -> 138997.28 | G29: =F29-SUM('📋 ACTIVOS'!H5:H29) -> -21870.76
A30: 🚨 Crisis severa | B30: -0.12 | C30: -0.5 | D30: -0.8 | E30: =(SUMIF('📋 ACTIVOS'!$B$5:$B$29,"RF",'📋 ACTIVOS'!$H$5:$H$29)/SUM('📋 ACTIVOS'!$H$5:$H$29))*B30+(SUMIF('📋 ACTIVOS'!$B$5:$B$29,"RV",'📋 ACTIVOS'!$H$5:$H$29)/SUM('📋 ACTIVOS'!$H$5:$H$29))*C30+(SUMIF('📋 ACTIVOS'!$B$5:$B$29,"CR",'📋 ACTIVOS'!$H$5:$H$29)/SUM('📋 ACTIVOS'!$H$5:$H$29))*D30 -> -0.21411172 | F30: =SUM('📋 ACTIVOS'!H5:H29)*(1+E30) -> 126424.31 | G30: =F30-SUM('📋 ACTIVOS'!H5:H29) -> -34443.732

Sheet 📅 HISTÓRICO
A1: 📅 REGISTRO HISTÓRICO — Evolución de la cartera en el tiempo (actualizar manualmente)
A2: Añade una fila nueva con la fecha y copia los valores del Dashboard. Los campos en azul son inputs manuales.
A4: Fecha | B4: Valor Cartera (€) | C4: Capital Invertido (€) | D4: G/P Total (€) | E4: Rent. Total % | F4: Peso RF % | G4: Peso RV % | H4: Peso Cripto % | I4: Rent. Esp. % | J4: Sharpe | K4: Notas
A5: 19/02/2026 | B5: 167020.52 | C5: 152966.48 | D5: 14028.82 | E5: 0.0917 | F5: 0.734 | G5: 0.218 | H5: 0.011 | I5: 0.0785 | J5: 0.74 | K5: Inicio seguimiento
A18: 📌 Instrucciones: Cada vez que actualices los precios en 📋 ACTIVOS, copia los valores calculados del 📊 DASHBOARD en una nueva fila aquí con la fecha.
