Workbook

Sheet ⚙️ INPUTS
A1: ⚙️ PARÁMETROS DE MERCADO — Editar valores en AZUL
A2: Tasa libre de riesgo (Rf) | B2: 0.02 | D2: Fuente: Euribor 12m ~ 2.4% | OAT 2Y ~ 2%
A3: Prima de riesgo mercado | B3: 0.055 | D3: Fuente: MSCI World histórico ~ 5-6%
A4: Inflación esperada (España) | B4: 0.025 | D4: Fuente: BCE objetivo 2%
A5: Tipo impositivo (IRPF) | B5: 0.19 | D5: Fuente: Primer tramo ganancias capital
A6: Comisiones medias RF | B6: 0.005 | D6: Fuente: Estimación fondos RF GVC
A7: Comisiones medias RV | B7: 0.015 | D7: Fuente: Estimación fondos RV GVC
A8: Rentabilidad objetivo cartera | B8: 0.08 | D8: Fuente: Objetivo personal
A9: Volatilidad objetivo máx. | B9: 0.12 | D9: Fuente: Tolerancia al riesgo moderada
A10: Ratio Sharpe objetivo | B10: 0.8 | D10: Fuente: Buena gestión riesgo/retorno
A12: CATEGORÍA | B12: Peso objetivo | D12: Peso actual (auto) | E12: Rent. esperada anual | F12: Volatilidad esperada | G12: Sharpe estimado
A13: Renta Fija (RF) | B13: 0.65 | D13: 0.7473 | E13: 0.065 | F13: 0.04 | G13: =(E13-$B$2)/F13
A14: Renta Variable (RV) | B14: 0.33 | D14: 0.2163 | E14: 0.12 | F14: 0.15 | G14: =(E14-$B$2)/F14
A15: Otros / SCR | B15: 0.02 | D15: 0.0364 | E15: 0 | F15: 0 | G15: —
A17: MÉTRICAS GLOBALES CALCULADAS | B17: Valor | D17: PARÁMETROS TEMPORALES | E17: Valor
A18: Rentabilidad esperada cartera | B18: 0.08185 | D18: Fecha cotización | E18: 22/02/2026
A19: Volatilidad esperada cartera | B19: 0.055912879 | D19: Horizonte inversión (años) | E19: 10
A20: Sharpe estimado cartera | B20: 1.1061852 | D20: Frecuencia rebalanceo | E20: Semestral
A21: Capital total invertido | B21: 150661.49 | D21: Benchmark RF | E21: GVC RF Horizonte
A22: Valor total cartera | B22: 165025.68 | D22: Benchmark RV | E22: MSCI World
A23: Ganancia / Pérdida total | B23: 14364.19
A24: Rentabilidad total real | B24: 0.09534082
A25: Rent. esperada 10 años | B25: 1.196193

Sheet 📋 ACTIVOS
A1: 📋 POSICIONES DE CARTERA — Datos reales a 22/02/2026 · Fuente: GVC Gaesco
A2: 🔵 AZUL = celda que actualizas tú | ⚫ NEGRO = fórmula automática | 🟡 AMARILLO = actualizar precio hoy | Añade nuevas filas antes de la fila TOTAL
A4: # | B4: Nombre del Activo | C4: Cat. | D4: Cuenta | E4: Nº Particip. | F4: Precio coste (€) | G4: Total invertido (€) | H4: Precio hoy (€) | I4: Valor actual (€) | J4: G/P (€) | K4: Rent. Total % | L4: YTD % | M4: MTD % | N4: Peso cartera % | O4: Fecha 1ª compra | P4: Rent. esperada cat. | Q4: Notas
A5: 1 | B5: GVC Gaesco RF Horizonte 2027 Clase A | C5: RF | D5: GB.70000505 | E5: 399.7037 | F5: 100.07 | G5: 40000 | H5: 115.24 | I5: 46060.31 | J5: 6060.31 | K5: 0.1515 | L5: 0.0015 | M5: 0.0005 | N5: 0.27911 | O5: 21/06/2023 | P5: ='⚙️ INPUTS'!E13 | Q5: Una compra única. Vence 2027.
A6: 2 | B6: GVC Gaesco Renta Fija Flexible FI A | C6: RF | D6: GB.70000505 + 70007162 | E6: 5452.3383 | F6: =G6/E6 | G6: 58131.75 | H6: 11.3 | I6: 61600.59 | J6: 3468.84 | K6: 0.0596 | L6: 0.0092 | M6: 0.0033 | N6: 0.373279 | O6: 21/05/2024 | P6: ='⚙️ INPUTS'!E13 | Q6: Posición en dos cuentas: 3360 (Eneko) + 2092 (conjunta)
A7: 3 | B7: GVC Gaesco Constantfons FI | C7: RF | D7: GB.70000505 | E7: 1523.5171 | F7: 9.47 | G7: 14419.56 | H7: 9.76 | I7: 14865.14 | J7: 445.58 | K7: 0.0309 | L7: 0.0026 | M7: 0.001 | N7: 0.090078 | O7: 21/06/2023 | P7: ='⚙️ INPUTS'!E13 | Q7: Fondo monetario/RF corto plazo
A8: 4 | B8: GVC Gaesco 300 Places World A | C8: RV | D8: Tres cuentas | E8: 455.60222 | F8: =G8/E8 | G8: 6205 | H8: 16.84 | I8: 7670.48 | J8: 1465.5 | K8: 0.2362 | L8: 0.038 | M8: 0.012 | N8: 0.046481 | O8: 20/12/2021 | P8: ='⚙️ INPUTS'!E14 | Q8: DCA mensual €50-120 desde dic 2021. Posición en 3 cuentas.
A9: 5 | B9: GVC Gaesco Japón FI | C9: RV | D9: Tres cuentas | E9: 286.13117 | F9: =G9/E9 | G9: 3555 | H9: 15.01 | I9: 4296.26 | J9: 741.26 | K9: 0.2085 | L9: 0.0128 | M9: 0.0042 | N9: 0.026034 | O9: 15/04/2024 | P9: ='⚙️ INPUTS'!E14 | Q9: DCA mensual desde abr 2024. Posición en 3 cuentas.
A10: 6 | B10: GVC Gaesco Value Minu A | C10: RV | D10: GB.70000506 | E10: 760.43286 | F10: 8.09 | G10: 6150.18 | H10: 9.14 | I10: 6953.1 | J10: 802.92 | K10: 0.1306 | L10: 0 | M10: 0 | N10: 0.042133 | O10: 05/12/2025 | P10: ='⚙️ INPUTS'!E14 | Q10: Compra única diciembre 2025
A11: 7 | B11: GVC Gaesco Zebra US Small Cap | C11: RV | D11: GB.70007162 | E11: 79.785203 | F11: =G11/E11 | G11: 7340 | H11: 100.34 | I11: 8005.43 | J11: 665.43 | K11: 0.0907 | L11: 0.0405 | M11: 0.027 | N11: 0.04851 | O11: 16/06/2025 | P11: ='⚙️ INPUTS'!E14 | Q11: DCA mensual desde jun 2025
A12: 8 | B12: GVC Gaesco Global Equity DS A | C12: RV | D12: GB.70007162 | E12: 116.74622 | F12: =G12/E12 | G12: 1800 | H12: 17.61 | I12: 2055.96 | J12: 255.96 | K12: 0.1422 | L12: 0.0142 | M12: 0.0049 | N12: 0.012458 | O12: 20/06/2025 | P12: ='⚙️ INPUTS'!E14 | Q12: DCA mensual desde jun 2025
A13: 9 | B13: GVC Gaesco Small Caps A | C13: RV | D13: GB.70007162 | E13: 91.886381 | F13: =G13/E13 | G13: 1440 | H13: 16.68 | I13: 1532.9 | J13: 92.9 | K13: 0.0645 | L13: 0.0064 | M13: 0.0022 | N13: 0.009289 | O13: 20/06/2025 | P13: ='⚙️ INPUTS'!E14 | Q13: DCA mensual desde jun 2025
A14: 10 | B14: GVC Gaesco Emergentfo | C14: RV | D14: GB.70007162 | E14: 4.69524 | F14: 238.55 | G14: 1120 | H14: 268.04 | I14: 1258.51 | J14: 138.51 | K14: 0.1237 | L14: 0.0124 | M14: 0.0037 | N14: 0.007626 | O14: 20/06/2025 | P14: ='⚙️ INPUTS'!E14 | Q14: DCA mensual mercados emergentes
A15: 11 | B15: GVC Gaesco V.I.F Clase A FI | C15: RV | D15: GB.70007162 | E15: 173.52365 | F15: 8.64 | G15: 1500 | H15: 8.98 | I15: 1558.79 | J15: 58.79 | K15: 0.0392 | L15: 0.0039 | M15: 0.0013 | N15: 0.009446 | O15: 20/06/2025 | P15: ='⚙️ INPUTS'!E14 | Q15: Value investing fund
A16: 12 | B16: Next Tier GVC Gaesco SCR | C16: SCR | D16: GB.70000505 | E16: 6000 | F16: 1 | G16: 6000 | H16: 1 | I16: 6000 | J16: 0 | K16: 0 | L16: 0 | M16: 0 | N16: 0.036358 | O16: 06/05/2025 | P16: 0 | Q16: Capital riesgo – precio no cotiza en mercado secundario
A17: 13 | B17: Fidelity MSCI World Index P EUR Acc | C17: RV | D17: Cuenta 1839035 | E17: 94.226 | F17: 11.67406 | G17: 1100 | H17: 12.609962 | I17: 1188.19 | J17: 88.19 | K17: 0.080172727 | L17: 0.0255 | M17: -0.0174 | N17: 0.0072 | O17: 28/03/2025 | P17: ='⚙️ INPUTS'!E14 | Q17: DCA €100/mes | ISIN IE00BYX5NX33 | VL 18/02/2026: 12.610€ | Fuente: quefondos.com
A18: 14 | B18: Fidelity S&P 500 Index P EUR Acc | C18: RV | D18: Cuenta 1819696 | E18: 81.6 | F18: 13.480392 | G18: 1100 | H18: 14.452367 | I18: 1179.31 | J18: 79.31 | K18: 0.0721 | L18: 0.0285 | M18: -0.0231 | N18: 0.007146 | O18: 28/03/2025 | P18: ='⚙️ INPUTS'!E14 | Q18: DCA €100/mes | ISIN IE00BYX5MX67 | VL 20/02/2026: 14.452€ | Fuente: quefondos.com
A19: 15 | B19: Pictet China Index P EUR | C19: RV | D19: Cuenta 1819696 | E19: 5.557 | F19: 143.96257 | G19: 800 | H19: 144.09 | I19: 800.71 | J19: 0.71 | K19: 0.0008875 | L19: 0.0949 | M19: -0.0234 | N19: 0.004852 | O19: 01/07/2025 | Q19: DCA €100/mes | ISIN LU0625737910 | VL ~144€ feb 2026 | Fuente: stockevents.app
A20: TOTAL CARTERA | G20: 150661.49 | I20: 165025.68 | J20: 14364.19 | K20: 0.09534082 | N20: 1
A21: 📌 CÓMO ACTUALIZAR: (1) Actualiza columna H «Precio hoy» con los valores liquidativos actuales de GVC (2) Actualiza columnas L y M con YTD% y MTD% del informe mensual (3) Para nuevas aportaciones: añade una fila antes de la fila TOTAL con el mismo formato (4) Guarda y sube el Excel al dashboard

Sheet 📊 DASHBOARD
A1: 📊 CUADRO DE MANDO — Cartera GVC Gaesco | Eneko Eguialde + Maite Hormaechea
A2: Datos a 22/02/2026 · Se actualiza automáticamente al subir el Excel al dashboard web
B4: 💰 VALOR TOTAL | E4: 📈 GANANCIA / PÉRDIDA | H4: 📊 RENT. TOTAL
B5: ='📋 ACTIVOS'!I20 | E5: ='📋 ACTIVOS'!J20 | H5: ='📋 ACTIVOS'!K20
B9: 💵 TOTAL INVERTIDO | E9: 📉 SHARPE EST. | H9: 🎯 RENT. ESPERADA
B10: ='📋 ACTIVOS'!G20 | E10: ='⚙️ INPUTS'!B20 | H10: ='⚙️ INPUTS'!B18
A16: RESUMEN POR CATEGORÍA
B17: Categoría | C17: Total Invertido | D17: Valor Actual | E17: G/P € | F17: Rent. Total | G17: YTD % | H17: Peso % | I17: Rent. Esp.
B18: 🟢 Renta Fija (RF) | C18: =SUMIF('📋 ACTIVOS'!C5:C19,"RF",'📋 ACTIVOS'!G5:G19) | D18: =SUMIF('📋 ACTIVOS'!C5:C19,"RF",'📋 ACTIVOS'!I5:I19) | E18: =SUMIF('📋 ACTIVOS'!C5:C19,"RF",'📋 ACTIVOS'!J5:J19) | F18: =IFERROR(D18/C18,0) | G18: =IFERROR(SUMPRODUCT(('📋 ACTIVOS'!C5:C19="RF")*'📋 ACTIVOS'!I5:I19*'📋 ACTIVOS'!L5:L19)/SUMIF('📋 ACTIVOS'!C5:C19,"RF",'📋 ACTIVOS'!I5:I19),0) | H18: =IFERROR(C18/SUM($C$18:$C$20),0) | J18: ='⚙️ INPUTS'!E13
B19: 🔵 Renta Variable (RV) | C19: =SUMIF('📋 ACTIVOS'!C5:C19,"RV",'📋 ACTIVOS'!G5:G19) | D19: =SUMIF('📋 ACTIVOS'!C5:C19,"RV",'📋 ACTIVOS'!I5:I19) | E19: =SUMIF('📋 ACTIVOS'!C5:C19,"RV",'📋 ACTIVOS'!J5:J19) | F19: =IFERROR(D19/C19,0) | G19: =IFERROR(SUMPRODUCT(('📋 ACTIVOS'!C5:C19="RV")*'📋 ACTIVOS'!I5:I19*'📋 ACTIVOS'!L5:L19)/SUMIF('📋 ACTIVOS'!C5:C19,"RV",'📋 ACTIVOS'!I5:I19),0) | H19: =IFERROR(C19/SUM($C$18:$C$20),0) | J19: ='⚙️ INPUTS'!E14
B20: 🟡 Otros / SCR | C20: =SUMIF('📋 ACTIVOS'!C5:C19,"SCR",'📋 ACTIVOS'!G5:G19) | D20: =SUMIF('📋 ACTIVOS'!C5:C19,"SCR",'📋 ACTIVOS'!I5:I19) | E20: =SUMIF('📋 ACTIVOS'!C5:C19,"SCR",'📋 ACTIVOS'!J5:J19) | F20: =IFERROR(D20/C20,0) | G20: =IFERROR(SUMPRODUCT(('📋 ACTIVOS'!C5:C19="SCR")*'📋 ACTIVOS'!I5:I19*'📋 ACTIVOS'!L5:L19)/SUMIF('📋 ACTIVOS'!C5:C19,"SCR",'📋 ACTIVOS'!I5:I19),0) | H20: =IFERROR(C20/SUM($C$18:$C$20),0) | J20: =0
B21: ⬛ TOTAL | C21: ='📋 ACTIVOS'!G20 | D21: ='📋 ACTIVOS'!I20 | E21: ='📋 ACTIVOS'!J20 | F21: ='📋 ACTIVOS'!K20 | G21: ='📋 ACTIVOS'!L20 | H21: =SUM(N18:N20) | J21: ='⚙️ INPUTS'!B18

Sheet 📈 HISTÓRICO
A1: 📈 EVOLUCIÓN HISTÓRICA DE CARTERA — Rellena manualmente al actualizar el Excel
A2: Cada vez que actualices el Excel, copia una nueva fila aquí con los valores del Dashboard · Esto construye el histórico para la gráfica de líneas
A4: Fecha | B4: Valor Total € | C4: Total Invest. € | D4: G/P € | E4: Rent. Total % | F4: Peso RF % | G4: Peso RV % | H4: Peso SCR % | I4: Sharpe Est. | J4: Notas
A5: 21/06/2023 | B5: 54000 | C5: 54419.56 | D5: -419.56 | E5: -0.0077 | F5: 0.85 | G5: 0.1 | H5: 0 | I5: 0 | J5: Primeras posiciones RF Horizonte + Constantfons
A6: 31/12/2023 | B6: 62000 | C6: 60000 | D6: 2000 | E6: 0.033 | F6: 0.8 | G6: 0.15 | H6: 0 | I6: 0.35 | J6: Fin de año 2023
A7: 21/05/2024 | B7: 98000 | C7: 95000 | D7: 3000 | E7: 0.032 | F7: 0.78 | G7: 0.17 | H7: 0 | I7: 0.4 | J7: Entra GVC RF Flexible Eneko
A8: 31/12/2024 | B8: 140000 | C8: 128000 | D8: 12000 | E8: 0.094 | F8: 0.72 | G8: 0.22 | H8: 0.04 | I8: 0.65 | J8: Fin de año 2024
A9: 20/06/2025 | B9: 148000 | C9: 133000 | D9: 15000 | E9: 0.113 | F9: 0.68 | G9: 0.25 | H9: 0.04 | I9: 0.7 | J9: Apertura cuenta conjunta GB.70007162
A10: 05/12/2025 | B10: 156000 | C10: 142000 | D10: 14000 | E10: 0.099 | F10: 0.65 | G10: 0.28 | H10: 0.04 | I10: 0.68 | J10: Entra GVC Value Minu
A11: 22/02/2026 | B11: ='📊 DASHBOARD'!C5 | C11: ='📊 DASHBOARD'!F5 | D11: =B11-C11 | E11: =IFERROR(D11/C11,0) | F11: ='📊 DASHBOARD'!? | G11: ='📊 DASHBOARD'!? | H11: ='📊 DASHBOARD'!? | J11: ← Datos actuales del Dashboard

Sheet 📉 HISTÓRICO POR ACTIVO
A1: 📉 HISTÓRICO DE RENTABILIDAD POR ACTIVO — Para gráficas individuales
A2: Rellena manualmente tras cada actualización · Columnas = fechas snapshot · Filas = activos
A4: Activo | B4: 21/06/2023 | C4: 31/12/2023 | D4: 31/12/2024 | E4: 20/06/2025 | F4: 22/02/2026
A5: GVC Gaesco RF Horizonte 2027 A | B5: — | C5: — | D5: 0.101 | E5: 0.1326 | F5: 0.1515
A6: GVC Gaesco RF Flexible FI A | B6: — | C6: — | D6: — | E6: 0.0219 | F6: 0.0703
A7: GVC Gaesco Constantfons FI | B7: 0 | C7: 0.018 | D7: 0.025 | E7: 0.028 | F7: 0.0309
A8: GVC Gaesco 300 Places World A | B8: — | C8: 0.08 | D8: 0.18 | E8: 0.22 | F8: 0.2702
A9: GVC Gaesco Japón FI | B9: — | C9: — | D9: — | E9: 0.18 | F9: 0.2258
A10: GVC Gaesco Value Minu A | B10: — | C10: — | D10: — | E10: — | F10: 0.1306
A11: GVC Gaesco Zebra US Small Cap | B11: — | C11: — | D11: — | E11: 0.08 | F11: 0.0907
A12: GVC Gaesco Global Equity DS A | B12: — | C12: — | D12: — | E12: 0.1 | F12: 0.1422
A13: GVC Gaesco Small Caps A | B13: — | C13: — | D13: — | E13: 0.04 | F13: 0.0645
A14: GVC Gaesco Emergentfo | B14: — | C14: — | D14: — | E14: 0.08 | F14: 0.1237
A15: GVC Gaesco V.I.F Clase A FI | B15: — | C15: — | D15: — | E15: 0.02 | F15: 0.0392
A16: Next Tier GVC SCR | B16: — | C16: — | D16: — | E16: — | F16: 0

Sheet 🔄 CÓMO ACTUALIZAR
A1: 🔄 GUÍA RÁPIDA DE ACTUALIZACIÓN
A4: ▶ CADA MES — Actualizar precios
B5: 1 | C5: Ve a la hoja '📋 ACTIVOS'
B6: 2 | C6: En la columna H (PRECIO HOY, fondo amarillo), introduce el valor liquidativo actual de cada fondo
B7: 3 | C7: Los valores los obtienes en: gvcgaesco.es → Mi Cartera → Informe de Posiciones
B8: 4 | C8: Las columnas I (Valor actual), J (G/P) y K (Rent. %) se recalculan automáticamente
B9: 5 | C9: Actualiza también L (YTD%) y M (MTD%) desde el informe mensual de GVC
B10: 6 | C10: Guarda el Excel y sube al dashboard web → todo actualizado
A12: ▶ NUEVA APORTACIÓN a un fondo existente
B13: 1 | C13: Ve a la hoja '📋 ACTIVOS'
B14: 2 | C14: Encuentra la fila del fondo al que has aportado
B15: 3 | C15: Actualiza la columna E (Nº participaciones) sumando las nuevas participaciones
B16: 4 | C16: Actualiza la columna G (Total invertido) sumando el importe aportado
B17: 5 | C17: La columna F (Precio coste medio) se recalcula sola
B18: 6 | C18: Guarda y sube
A20: ▶ NUEVA POSICIÓN (fondo nuevo)
B21: 1 | C21: Ve a la hoja '📋 ACTIVOS'
B22: 2 | C22: Inserta una fila nueva antes de la fila TOTAL (clic derecho → Insertar fila)
B23: 3 | C23: Copia el formato de la fila anterior
B24: 4 | C24: Rellena: Nombre (col B), Cat. RF/RV/SCR (col C), Cuenta (col D)
B25: 5 | C25: Introduce participaciones (E), precio coste (F), total invertido (G), precio hoy (H)
B26: 6 | C26: Copia las fórmulas de las columnas I a N desde la fila de arriba
B27: 7 | C27: Añade fecha de primera compra (col O) y notas (col Q)
A29: ▶ REGISTRAR SNAPSHOT HISTÓRICO
B30: 1 | C30: Ve a la hoja '📈 HISTÓRICO'
B31: 2 | C31: Añade una nueva fila al final de los datos existentes
B32: 3 | C32: Introduce la fecha de hoy (col A)
B33: 4 | C33: Copia los valores del Dashboard: Valor Total, Invertido, G/P, Rent.%, pesos por categoría
B34: 5 | C34: Esto construye la gráfica de líneas histórica
